dbrownell_devtools_test/Add.py
dbrownell_devtools_test/__init__.py
dbrownell_devtools_test-0.3.1.dist-info/METADATA
dbrownell_devtools_test-0.3.1.dist-info/WHEEL
dbrownell_devtools_test-0.3.1.dist-info/top_level.txt
dbrownell_devtools_test-0.3.1.dist-info/RECORD
